{
  "fetched_at": "2026-04-23T10:09:17+0000",
  "url": "https://xz.chsi.com.cn/speciality/detail/zyjy.action?specId=pisuaw667u74u5mo",
  "spec_id": "pisuaw667u74u5mo",
  "page_title": "智能安防运营管理_专业洞察_学职平台",
  "basic": {
    "name": "智能安防运营管理",
    "level": "高职（专科）",
    "code": "580703",
    "discipline": "",
    "major_class": "安全防范类",
    "detail_url": "https://xz.chsi.com.cn/speciality/detail/zyjy.action?specId=pisuaw667u74u5mo",
    "spec_id": "pisuaw667u74u5mo",
    "list_meta": {
      "专业名称": "智能安防运营管理",
      "专业代码": "580703",
      "层次": "高职（专科）",
      "门类代码": "106058",
      "门类名称": "公安与司法",
      "专业类": "安全防范类",
      "专业原始ID": "x0ko6i0dwylko95i",
      "评价人数": 0,
      "综合满意度": 0
    }
  },
  "detected_headings": [
    "专业介绍",
    "统计信息",
    "专业满意度",
    "学习投入意愿",
    "学长学姐有话说",
    "开设院校",
    "课程统计",
    "开设课程",
    "升学路径",
    "升学情况",
    "升学指数",
    "从业情况",
    "薪酬指数",
    "已毕业学生主要就业省份",
    "专业能力",
    "资质证书"
  ],
  "sections": {
    "专业介绍": {
      "raw_text": "该数据来源于教育部《职业教育专业教学标准-2025年修（制）订》文件。\n本专业培养掌握智能安防运营管理专业知识和技术技能，具备职业综合素质和行动能力，面向安全保护服务行业的安全保护服务人员等职业，能够从事报警信息接收、信息研判与处置、监测智能安防系统运行状态、提供系统优化建议等工作的高技能人才。\n查看更多",
      "line_count": 3,
      "lines": [
        "该数据来源于教育部《职业教育专业教学标准-2025年修（制）订》文件。",
        "本专业培养掌握智能安防运营管理专业知识和技术技能，具备职业综合素质和行动能力，面向安全保护服务行业的安全保护服务人员等职业，能够从事报警信息接收、信息研判与处置、监测智能安防系统运行状态、提供系统优化建议等工作的高技能人才。",
        "查看更多"
      ]
    },
    "统计信息": {
      "raw_text": "数据统计截止日期：2024年12月31日\n全国普通高校毕业生规模（人）\n100-150人",
      "line_count": 3,
      "lines": [
        "数据统计截止日期：2024年12月31日",
        "全国普通高校毕业生规模（人）",
        "100-150人"
      ]
    },
    "专业满意度": {
      "raw_text": "评价人数较少，暂无满意度信息，本专业学生可点击参与调查\n专业满意度调查",
      "line_count": 2,
      "lines": [
        "评价人数较少，暂无满意度信息，本专业学生可点击参与调查",
        "专业满意度调查"
      ]
    },
    "学长学姐有话说": {
      "raw_text": "我要评价\n相近专业\n安全防范技术\n安全保卫管理\n专题推荐\n更多\n学信网 版权声明 鸣谢单位 关于我们 联系我们\n主办单位：教育部学生服务与素质发展中心\nCopyright © 2003-2026 学信网 All Rights Reserved\n京ICP备19004913号-1 京公网安备11010202009747号\n客服热线：010-67410388\n客服邮箱：kefu@chsi.com.cn\n官方微信",
      "line_count": 13,
      "lines": [
        "我要评价",
        "相近专业",
        "安全防范技术",
        "安全保卫管理",
        "专题推荐",
        "更多",
        "学信网 版权声明 鸣谢单位 关于我们 联系我们",
        "主办单位：教育部学生服务与素质发展中心",
        "Copyright © 2003-2026 学信网 All Rights Reserved",
        "京ICP备19004913号-1 京公网安备11010202009747号",
        "客服热线：010-67410388",
        "客服邮箱：kefu@chsi.com.cn",
        "官方微信"
      ]
    },
    "开设院校": {
      "raw_text": "全国(9)\n北京(1)\n江苏(1)\n浙江(1)\n山东(1)\n湖北(1)\n重庆(1)\n四川(3)\n专科高校：\n骨干专科\n示范专科\n院校名称 推荐指数 专业满意度\n综合情况 办学条件 教学质量 就业\n北京政法职业学院 - 0.0 0人 0.0 0人 0.0 0人 0.0 0人\n浙江警官职业学院 - 0.0 0人 0.0 0人 0.0 0人 0.0 0人\n武汉警官职业学院 - 5.0 1人 5.0 4人 5.0 1人 5.0 1人\n四川司法警官职业学院 - 0.0 0人 3.0 1人 0.0 0人 0.0 0人\n山东司法警官职业学院 - 0.0 0人 0.0 0人 0.0 0人 0.0 0人\n四川现代职业学院 - 0.0 0人 0.0 0人 0.0 0人 0.0 0人\n重庆轻工职业学院 5.0 12人 1.0 1人 3.2 6人 3.0 3人 1.0 1人\n江苏安全技术职业学院 4.0 8人 0.0 0人 0.0 0人 0.0 0人 0.0 0人\n德阳科贸职业学院 - 0.0 0人 0.0 0人 0.0 0人 0.0 0人",
      "line_count": 22,
      "lines": [
        "全国(9)",
        "北京(1)",
        "江苏(1)",
        "浙江(1)",
        "山东(1)",
        "湖北(1)",
        "重庆(1)",
        "四川(3)",
        "专科高校：",
        "骨干专科",
        "示范专科",
        "院校名称 推荐指数 专业满意度",
        "综合情况 办学条件 教学质量 就业",
        "北京政法职业学院 - 0.0 0人 0.0 0人 0.0 0人 0.0 0人",
        "浙江警官职业学院 - 0.0 0人 0.0 0人 0.0 0人 0.0 0人",
        "武汉警官职业学院 - 5.0 1人 5.0 4人 5.0 1人 5.0 1人",
        "四川司法警官职业学院 - 0.0 0人 3.0 1人 0.0 0人 0.0 0人",
        "山东司法警官职业学院 - 0.0 0人 0.0 0人 0.0 0人 0.0 0人",
        "四川现代职业学院 - 0.0 0人 0.0 0人 0.0 0人 0.0 0人",
        "重庆轻工职业学院 5.0 12人 1.0 1人 3.2 6人 3.0 3人 1.0 1人",
        "江苏安全技术职业学院 4.0 8人 0.0 0人 0.0 0人 0.0 0人 0.0 0人",
        "德阳科贸职业学院 - 0.0 0人 0.0 0人 0.0 0人 0.0 0人"
      ]
    },
    "开设课程": {
      "raw_text": "+ 我要补充课程\n参考专业课程\n课程名称 课程类型\n智能安全防范系统应用\n专业核心课程\n警情信息分析与研判\n专业核心课程\n警情处置\n专业核心课程\n智能安防系统巡检\n专业核心课程\n智能安防系统故障分析与处理\n专业核心课程\n重要场所技术防范规划\n专业核心课程\n习近平法治思想概论\n专业基础课程\n宪法与法学基础\n专业基础课程\n安保法律法规\n专业基础课程\n管理学基础\n专业基础课程\n共 14 条 1 2 跳至 页",
      "line_count": 24,
      "lines": [
        "+ 我要补充课程",
        "参考专业课程",
        "课程名称 课程类型",
        "智能安全防范系统应用",
        "专业核心课程",
        "警情信息分析与研判",
        "专业核心课程",
        "警情处置",
        "专业核心课程",
        "智能安防系统巡检",
        "专业核心课程",
        "智能安防系统故障分析与处理",
        "专业核心课程",
        "重要场所技术防范规划",
        "专业核心课程",
        "习近平法治思想概论",
        "专业基础课程",
        "宪法与法学基础",
        "专业基础课程",
        "安保法律法规",
        "专业基础课程",
        "管理学基础",
        "专业基础课程",
        "共 14 条 1 2 跳至 页"
      ]
    },
    "升学路径": {
      "raw_text": "本科\n高职本科\n数字安防技术\n普通本科\n安全防范工程\n治安学\n安全工程",
      "line_count": 7,
      "lines": [
        "本科",
        "高职本科",
        "数字安防技术",
        "普通本科",
        "安全防范工程",
        "治安学",
        "安全工程"
      ]
    },
    "升学情况": {
      "raw_text": "升学路径该数据来源于教育部《职业教育专业简介-2022年修订》文件与中国研究生招生信息网。\n本科\n高职本科\n数字安防技术\n普通本科\n安全防范工程\n治安学\n安全工程",
      "line_count": 8,
      "lines": [
        "升学路径该数据来源于教育部《职业教育专业简介-2022年修订》文件与中国研究生招生信息网。",
        "本科",
        "高职本科",
        "数字安防技术",
        "普通本科",
        "安全防范工程",
        "治安学",
        "安全工程"
      ]
    },
    "专业能力": {
      "raw_text": "该数据来源于教育部《职业教育专业教学标准-2025年修（制）订》文件。\n根据该专业培养目标，学习本专业将可能获取的能力有：\n1. 掌握智能安防系统基本原理及使用方法等基础理论知识\n2. 掌握警情处理步骤及信息分析原则等理论知识\n3. 掌握高效运用智能安防系统接收报警信息等技术，具有分析判断及正确处置警情的能力\n4. 掌握智能安防系统故障排除与方案设计规则等技术，具备监测运行状态、处理异常故障及优化系统的能力\n5. 掌握信息技术基础知识，具有适应本行业数字化和智能化发展需求的数字技能",
      "line_count": 7,
      "lines": [
        "该数据来源于教育部《职业教育专业教学标准-2025年修（制）订》文件。",
        "根据该专业培养目标，学习本专业将可能获取的能力有：",
        "1. 掌握智能安防系统基本原理及使用方法等基础理论知识",
        "2. 掌握警情处理步骤及信息分析原则等理论知识",
        "3. 掌握高效运用智能安防系统接收报警信息等技术，具有分析判断及正确处置警情的能力",
        "4. 掌握智能安防系统故障排除与方案设计规则等技术，具备监测运行状态、处理异常故障及优化系统的能力",
        "5. 掌握信息技术基础知识，具有适应本行业数字化和智能化发展需求的数字技能"
      ]
    },
    "资质证书": {
      "raw_text": "该数据来源于教育部《职业教育专业教学标准-2025年修（制）订》文件。\n根据该专业未来职业面向，可以选择考取的职业证书有：\n保安员\n综合安防系统建设与运维\n安全防范系统建设与运维\n智慧安防系统实施与运维",
      "line_count": 6,
      "lines": [
        "该数据来源于教育部《职业教育专业教学标准-2025年修（制）订》文件。",
        "根据该专业未来职业面向，可以选择考取的职业证书有：",
        "保安员",
        "综合安防系统建设与运维",
        "安全防范系统建设与运维",
        "智慧安防系统实施与运维"
      ]
    }
  },
  "tables": [
    {
      "index": 1,
      "rows": [
        [
          "院校名称",
          "推荐指数",
          "专业满意度"
        ],
        [
          "综合情况",
          "办学条件",
          "教学质量",
          "就业"
        ],
        [
          "北京政法职业学院",
          "-",
          "0.0 0人",
          "0.0 0人",
          "0.0 0人",
          "0.0 0人"
        ],
        [
          "浙江警官职业学院",
          "-",
          "0.0 0人",
          "0.0 0人",
          "0.0 0人",
          "0.0 0人"
        ],
        [
          "武汉警官职业学院",
          "-",
          "5.0 1人",
          "5.0 4人",
          "5.0 1人",
          "5.0 1人"
        ],
        [
          "四川司法警官职业学院",
          "-",
          "0.0 0人",
          "3.0 1人",
          "0.0 0人",
          "0.0 0人"
        ],
        [
          "山东司法警官职业学院",
          "-",
          "0.0 0人",
          "0.0 0人",
          "0.0 0人",
          "0.0 0人"
        ],
        [
          "四川现代职业学院",
          "-",
          "0.0 0人",
          "0.0 0人",
          "0.0 0人",
          "0.0 0人"
        ],
        [
          "重庆轻工职业学院",
          "5.0 12人",
          "1.0 1人",
          "3.2 6人",
          "3.0 3人",
          "1.0 1人"
        ],
        [
          "江苏安全技术职业学院",
          "4.0 8人",
          "0.0 0人",
          "0.0 0人",
          "0.0 0人",
          "0.0 0人"
        ],
        [
          "德阳科贸职业学院",
          "-",
          "0.0 0人",
          "0.0 0人",
          "0.0 0人",
          "0.0 0人"
        ]
      ]
    },
    {
      "index": 2,
      "rows": [
        [
          "课程名称",
          "课程类型"
        ],
        [
          "智能安全防范系统应用",
          "专业核心课程"
        ],
        [
          "警情信息分析与研判",
          "专业核心课程"
        ],
        [
          "警情处置",
          "专业核心课程"
        ],
        [
          "智能安防系统巡检",
          "专业核心课程"
        ],
        [
          "智能安防系统故障分析与处理",
          "专业核心课程"
        ],
        [
          "重要场所技术防范规划",
          "专业核心课程"
        ],
        [
          "习近平法治思想概论",
          "专业基础课程"
        ],
        [
          "宪法与法学基础",
          "专业基础课程"
        ],
        [
          "安保法律法规",
          "专业基础课程"
        ],
        [
          "管理学基础",
          "专业基础课程"
        ]
      ]
    }
  ],
  "courses": {
    "count": 10,
    "items": [
      {
        "course_name": "智能安全防范系统应用",
        "course_type": "专业核心课程",
        "source": "table_course_type"
      },
      {
        "course_name": "警情信息分析与研判",
        "course_type": "专业核心课程",
        "source": "table_course_type"
      },
      {
        "course_name": "警情处置",
        "course_type": "专业核心课程",
        "source": "table_course_type"
      },
      {
        "course_name": "智能安防系统巡检",
        "course_type": "专业核心课程",
        "source": "table_course_type"
      },
      {
        "course_name": "智能安防系统故障分析与处理",
        "course_type": "专业核心课程",
        "source": "table_course_type"
      },
      {
        "course_name": "重要场所技术防范规划",
        "course_type": "专业核心课程",
        "source": "table_course_type"
      },
      {
        "course_name": "习近平法治思想概论",
        "course_type": "专业基础课程",
        "source": "table_course_type"
      },
      {
        "course_name": "宪法与法学基础",
        "course_type": "专业基础课程",
        "source": "table_course_type"
      },
      {
        "course_name": "安保法律法规",
        "course_type": "专业基础课程",
        "source": "table_course_type"
      },
      {
        "course_name": "管理学基础",
        "course_type": "专业基础课程",
        "source": "table_course_type"
      }
    ],
    "sources": {
      "dom_count": 10,
      "api_count": 0
    }
  },
  "offering_schools": {
    "count": 10,
    "summary": {
      "national_total": 9,
      "province_counts": [
        {
          "province": "北京",
          "count": 1
        },
        {
          "province": "江苏",
          "count": 1
        },
        {
          "province": "浙江",
          "count": 1
        },
        {
          "province": "山东",
          "count": 1
        },
        {
          "province": "湖北",
          "count": 1
        },
        {
          "province": "重庆",
          "count": 1
        },
        {
          "province": "四川",
          "count": 3
        }
      ],
      "school_type_tags": [
        "专科高校"
      ]
    },
    "items": [
      {
        "school_name": "北京政法职业学院",
        "school_url": "https://gaokao.chsi.com.cn/sch/schoolInfoMain--schId-1067.dhtml",
        "recommend_index": 0,
        "recommend_votes": 0,
        "school_type": "公办",
        "source": "api",
        "raw": {
          "academeId": "1067",
          "bxxz": "公办",
          "mydList": [
            {
              "count": 0,
              "rank": 0,
              "type": "3",
              "typeDesc": "综合满意度"
            },
            {
              "count": 0,
              "rank": 0,
              "type": "0",
              "typeDesc": "办学条件满意度"
            },
            {
              "count": 0,
              "rank": 0,
              "type": "1",
              "typeDesc": "教学质量满意度"
            },
            {
              "count": 0,
              "rank": 0,
              "type": "2",
              "typeDesc": "就业满意度"
            }
          ],
          "schId": "73398398",
          "yxdm": "12451",
          "yxmc": "北京政法职业学院",
          "yxmydList": [
            {
              "count": 502,
              "rank": 3.3,
              "type": "2",
              "typeDesc": "综合满意度"
            },
            {
              "count": 574,
              "rank": 3.3,
              "type": "0",
              "typeDesc": "院校环境满意度"
            },
            {
              "count": 481,
              "rank": 3.1,
              "type": "1",
              "typeDesc": "生活满意度"
            }
          ],
          "zytjCount": 0,
          "zytjRank": 0
        },
        "columns": [
          "-",
          "0.0 0人",
          "0.0 0人",
          "0.0 0人",
          "0.0 0人"
        ]
      },
      {
        "school_name": "浙江警官职业学院",
        "school_url": "https://gaokao.chsi.com.cn/sch/schoolInfoMain--schId-1343.dhtml",
        "recommend_index": 0,
        "recommend_votes": 0,
        "school_type": "公办",
        "source": "api",
        "raw": {
          "academeId": "1343",
          "bxxz": "公办",
          "mydList": [
            {
              "count": 0,
              "rank": 0,
              "type": "3",
              "typeDesc": "综合满意度"
            },
            {
              "count": 0,
              "rank": 0,
              "type": "0",
              "typeDesc": "办学条件满意度"
            },
            {
              "count": 0,
              "rank": 0,
              "type": "1",
              "typeDesc": "教学质量满意度"
            },
            {
              "count": 0,
              "rank": 0,
              "type": "2",
              "typeDesc": "就业满意度"
            }
          ],
          "schId": "73389584",
          "yxdm": "12869",
          "yxmc": "浙江警官职业学院",
          "yxmydList": [
            {
              "count": 761,
              "rank": 4.1,
              "type": "2",
              "typeDesc": "综合满意度"
            },
            {
              "count": 922,
              "rank": 4.2,
              "type": "0",
              "typeDesc": "院校环境满意度"
            },
            {
              "count": 716,
              "rank": 3.8,
              "type": "1",
              "typeDesc": "生活满意度"
            }
          ],
          "zytjCount": 0,
          "zytjRank": 0
        },
        "columns": [
          "-",
          "0.0 0人",
          "0.0 0人",
          "0.0 0人",
          "0.0 0人"
        ]
      },
      {
        "school_name": "武汉警官职业学院",
        "school_url": "https://gaokao.chsi.com.cn/sch/schoolInfoMain--schId-1456.dhtml",
        "recommend_index": 0,
        "recommend_votes": 0,
        "school_type": "公办",
        "source": "api",
        "raw": {
          "academeId": "1456",
          "bxxz": "公办",
          "mydList": [
            {
              "count": 1,
              "rank": 5,
              "type": "3",
              "typeDesc": "综合满意度"
            },
            {
              "count": 4,
              "rank": 5,
              "type": "0",
              "typeDesc": "办学条件满意度"
            },
            {
              "count": 1,
              "rank": 5,
              "type": "1",
              "typeDesc": "教学质量满意度"
            },
            {
              "count": 1,
              "rank": 5,
              "type": "2",
              "typeDesc": "就业满意度"
            }
          ],
          "schId": "73389976",
          "yxdm": "12984",
          "yxmc": "武汉警官职业学院",
          "yxmydList": [
            {
              "count": 1187,
              "rank": 3.2,
              "type": "2",
              "typeDesc": "综合满意度"
            },
            {
              "count": 1661,
              "rank": 3.1,
              "type": "0",
              "typeDesc": "院校环境满意度"
            },
            {
              "count": 1144,
              "rank": 2.8,
              "type": "1",
              "typeDesc": "生活满意度"
            }
          ],
          "zytjCount": 0,
          "zytjRank": 0
        },
        "columns": [
          "-",
          "5.0 1人",
          "5.0 4人",
          "5.0 1人",
          "5.0 1人"
        ]
      },
      {
        "school_name": "四川司法警官职业学院",
        "school_url": "https://gaokao.chsi.com.cn/sch/schoolInfoMain--schId-2052.dhtml",
        "recommend_index": 0,
        "recommend_votes": 0,
        "school_type": "公办",
        "source": "api",
        "raw": {
          "academeId": "2052",
          "bxxz": "公办",
          "mydList": [
            {
              "count": 0,
              "rank": 0,
              "type": "3",
              "typeDesc": "综合满意度"
            },
            {
              "count": 1,
              "rank": 3,
              "type": "0",
              "typeDesc": "办学条件满意度"
            },
            {
              "count": 0,
              "rank": 0,
              "type": "1",
              "typeDesc": "教学质量满意度"
            },
            {
              "count": 0,
              "rank": 0,
              "type": "2",
              "typeDesc": "就业满意度"
            }
          ],
          "schId": "73392056",
          "yxdm": "13813",
          "yxmc": "四川司法警官职业学院",
          "yxmydList": [
            {
              "count": 884,
              "rank": 3.8,
              "type": "2",
              "typeDesc": "综合满意度"
            },
            {
              "count": 1163,
              "rank": 3.8,
              "type": "0",
              "typeDesc": "院校环境满意度"
            },
            {
              "count": 827,
              "rank": 3.4,
              "type": "1",
              "typeDesc": "生活满意度"
            }
          ],
          "zytjCount": 0,
          "zytjRank": 0
        },
        "columns": [
          "-",
          "0.0 0人",
          "3.0 1人",
          "0.0 0人",
          "0.0 0人"
        ]
      },
      {
        "school_name": "山东司法警官职业学院",
        "school_url": "https://gaokao.chsi.com.cn/sch/schoolInfoMain--schId-5280172.dhtml",
        "recommend_index": 0,
        "recommend_votes": 0,
        "school_type": "公办",
        "source": "api",
        "raw": {
          "academeId": "5280172",
          "bxxz": "公办",
          "mydList": [
            {
              "count": 0,
              "rank": 0,
              "type": "3",
              "typeDesc": "综合满意度"
            },
            {
              "count": 0,
              "rank": 0,
              "type": "0",
              "typeDesc": "办学条件满意度"
            },
            {
              "count": 0,
              "rank": 0,
              "type": "1",
              "typeDesc": "教学质量满意度"
            },
            {
              "count": 0,
              "rank": 0,
              "type": "2",
              "typeDesc": "就业满意度"
            }
          ],
          "schId": "73392940",
          "yxdm": "14082",
          "yxmc": "山东司法警官职业学院",
          "yxmydList": [
            {
              "count": 1276,
              "rank": 3.9,
              "type": "2",
              "typeDesc": "综合满意度"
            },
            {
              "count": 1707,
              "rank": 3.9,
              "type": "0",
              "typeDesc": "院校环境满意度"
            },
            {
              "count": 1189,
              "rank": 3.6,
              "type": "1",
              "typeDesc": "生活满意度"
            }
          ],
          "zytjCount": 0,
          "zytjRank": 0
        },
        "columns": [
          "-",
          "0.0 0人",
          "0.0 0人",
          "0.0 0人",
          "0.0 0人"
        ]
      },
      {
        "school_name": "四川现代职业学院",
        "school_url": "https://gaokao.chsi.com.cn/sch/schoolInfoMain--schId-14779825.dhtml",
        "recommend_index": 0,
        "recommend_votes": 0,
        "school_type": "民办",
        "source": "api",
        "raw": {
          "academeId": "14779825",
          "bxxz": "民办",
          "mydList": [
            {
              "count": 0,
              "rank": 0,
              "type": "3",
              "typeDesc": "综合满意度"
            },
            {
              "count": 0,
              "rank": 0,
              "type": "0",
              "typeDesc": "办学条件满意度"
            },
            {
              "count": 0,
              "rank": 0,
              "type": "1",
              "typeDesc": "教学质量满意度"
            },
            {
              "count": 0,
              "rank": 0,
              "type": "2",
              "typeDesc": "就业满意度"
            }
          ],
          "schId": "73393201",
          "yxdm": "14176",
          "yxmc": "四川现代职业学院",
          "yxmydList": [
            {
              "count": 1306,
              "rank": 3.3,
              "type": "2",
              "typeDesc": "综合满意度"
            },
            {
              "count": 1936,
              "rank": 3.6,
              "type": "0",
              "typeDesc": "院校环境满意度"
            },
            {
              "count": 1260,
              "rank": 2.6,
              "type": "1",
              "typeDesc": "生活满意度"
            }
          ],
          "zytjCount": 0,
          "zytjRank": 0
        },
        "columns": [
          "-",
          "0.0 0人",
          "0.0 0人",
          "0.0 0人",
          "0.0 0人"
        ]
      },
      {
        "school_name": "重庆轻工职业学院",
        "school_url": "https://gaokao.chsi.com.cn/sch/schoolInfoMain--schId-174255950.dhtml",
        "recommend_index": 5,
        "recommend_votes": 12,
        "school_type": "民办",
        "source": "api",
        "raw": {
          "academeId": "174255950",
          "bxxz": "民办",
          "mydList": [
            {
              "count": 1,
              "rank": 1,
              "type": "3",
              "typeDesc": "综合满意度"
            },
            {
              "count": 6,
              "rank": 3.2,
              "type": "0",
              "typeDesc": "办学条件满意度"
            },
            {
              "count": 3,
              "rank": 3,
              "type": "1",
              "typeDesc": "教学质量满意度"
            },
            {
              "count": 1,
              "rank": 1,
              "type": "2",
              "typeDesc": "就业满意度"
            }
          ],
          "schId": "203682066",
          "yxdm": "14368",
          "yxmc": "重庆轻工职业学院",
          "yxmydList": [
            {
              "count": 101,
              "rank": 4,
              "type": "2",
              "typeDesc": "综合满意度"
            },
            {
              "count": 91,
              "rank": 4.3,
              "type": "0",
              "typeDesc": "院校环境满意度"
            },
            {
              "count": 88,
              "rank": 4,
              "type": "1",
              "typeDesc": "生活满意度"
            }
          ],
          "zytjCount": 12,
          "zytjRank": 5
        },
        "columns": [
          "5.0 12人",
          "1.0 1人",
          "3.2 6人",
          "3.0 3人",
          "1.0 1人"
        ]
      },
      {
        "school_name": "江苏安全技术职业学院",
        "school_url": "https://gaokao.chsi.com.cn/sch/schoolInfoMain--schId-1683515433.dhtml",
        "recommend_index": 4,
        "recommend_votes": 8,
        "school_type": "公办",
        "source": "api",
        "raw": {
          "academeId": "1683515433",
          "bxxz": "公办",
          "mydList": [
            {
              "count": 0,
              "rank": 0,
              "type": "3",
              "typeDesc": "综合满意度"
            },
            {
              "count": 0,
              "rank": 0,
              "type": "0",
              "typeDesc": "办学条件满意度"
            },
            {
              "count": 0,
              "rank": 0,
              "type": "1",
              "typeDesc": "教学质量满意度"
            },
            {
              "count": 0,
              "rank": 0,
              "type": "2",
              "typeDesc": "就业满意度"
            }
          ],
          "schId": "a512cjpilqfmyvbk",
          "yxdm": "14589",
          "yxmc": "江苏安全技术职业学院",
          "yxmydList": [
            {
              "count": 101,
              "rank": 3.4,
              "type": "2",
              "typeDesc": "综合满意度"
            },
            {
              "count": 147,
              "rank": 3.8,
              "type": "0",
              "typeDesc": "院校环境满意度"
            },
            {
              "count": 93,
              "rank": 3.5,
              "type": "1",
              "typeDesc": "生活满意度"
            }
          ],
          "zytjCount": 8,
          "zytjRank": 4
        },
        "columns": [
          "4.0 8人",
          "0.0 0人",
          "0.0 0人",
          "0.0 0人",
          "0.0 0人"
        ]
      },
      {
        "school_name": "德阳科贸职业学院",
        "school_url": "https://gaokao.chsi.com.cn/sch/schoolInfoMain--schId-2252064232.dhtml",
        "recommend_index": 0,
        "recommend_votes": 0,
        "school_type": "民办",
        "source": "api",
        "raw": {
          "academeId": "2252064232",
          "bxxz": "民办",
          "mydList": [
            {
              "count": 0,
              "rank": 0,
              "type": "3",
              "typeDesc": "综合满意度"
            },
            {
              "count": 0,
              "rank": 0,
              "type": "0",
              "typeDesc": "办学条件满意度"
            },
            {
              "count": 0,
              "rank": 0,
              "type": "1",
              "typeDesc": "教学质量满意度"
            },
            {
              "count": 0,
              "rank": 0,
              "type": "2",
              "typeDesc": "就业满意度"
            }
          ],
          "schId": "foywrgocmq84wpii",
          "yxdm": "14643",
          "yxmc": "德阳科贸职业学院",
          "yxmydList": [
            {
              "count": 143,
              "rank": 3.7,
              "type": "2",
              "typeDesc": "综合满意度"
            },
            {
              "count": 463,
              "rank": 3.8,
              "type": "0",
              "typeDesc": "院校环境满意度"
            },
            {
              "count": 138,
              "rank": 3.5,
              "type": "1",
              "typeDesc": "生活满意度"
            }
          ],
          "zytjCount": 0,
          "zytjRank": 0
        },
        "columns": [
          "-",
          "0.0 0人",
          "0.0 0人",
          "0.0 0人",
          "0.0 0人"
        ]
      },
      {
        "school_name": "综合情况",
        "school_url": "",
        "columns": [
          "办学条件",
          "教学质量",
          "就业"
        ],
        "source": "table"
      }
    ],
    "sources": {
      "dom_count": 10,
      "api_count": 9,
      "school_link_count": 9
    }
  },
  "charts": {
    "count": 2,
    "items": [
      {
        "index": 1,
        "section": "图表",
        "src": "https://t3.chei.com.cn/xzpt/survey/cdn/showimg/86ste2hx8nk5qpbe.jpeg",
        "alt": "",
        "title": "",
        "width": 240,
        "height": 86,
        "local_path": "output/xz_detail/details/pisuaw667u74u5mo/images/e0cdde5b9d25.jpeg",
        "file_size": 38765,
        "content_type": "image/jpeg",
        "error": ""
      },
      {
        "index": 2,
        "section": "图表",
        "src": "https://t3.chei.com.cn/xzpt/survey/cdn/showimg/ifnanakjkyxfh59z.jpeg",
        "alt": "",
        "title": "",
        "width": 240,
        "height": 86,
        "local_path": "output/xz_detail/details/pisuaw667u74u5mo/images/fb592bf2e80d.jpeg",
        "file_size": 24561,
        "content_type": "image/jpeg",
        "error": ""
      }
    ]
  },
  "tab_links": [],
  "key_links": [
    {
      "text": "北京政法职业学院",
      "href": "https://gaokao.chsi.com.cn/sch/schoolInfoMain--schId-1067.dhtml"
    },
    {
      "text": "浙江警官职业学院",
      "href": "https://gaokao.chsi.com.cn/sch/schoolInfoMain--schId-1343.dhtml"
    },
    {
      "text": "武汉警官职业学院",
      "href": "https://gaokao.chsi.com.cn/sch/schoolInfoMain--schId-1456.dhtml"
    },
    {
      "text": "四川司法警官职业学院",
      "href": "https://gaokao.chsi.com.cn/sch/schoolInfoMain--schId-2052.dhtml"
    },
    {
      "text": "山东司法警官职业学院",
      "href": "https://gaokao.chsi.com.cn/sch/schoolInfoMain--schId-5280172.dhtml"
    },
    {
      "text": "四川现代职业学院",
      "href": "https://gaokao.chsi.com.cn/sch/schoolInfoMain--schId-14779825.dhtml"
    },
    {
      "text": "重庆轻工职业学院",
      "href": "https://gaokao.chsi.com.cn/sch/schoolInfoMain--schId-174255950.dhtml"
    },
    {
      "text": "江苏安全技术职业学院",
      "href": "https://gaokao.chsi.com.cn/sch/schoolInfoMain--schId-1683515433.dhtml"
    },
    {
      "text": "德阳科贸职业学院",
      "href": "https://gaokao.chsi.com.cn/sch/schoolInfoMain--schId-2252064232.dhtml"
    },
    {
      "text": "安全防范技术",
      "href": "https://xz.chsi.com.cn/speciality/detail.action?specId=izj6brp95doxsc9e"
    },
    {
      "text": "安全保卫管理",
      "href": "https://xz.chsi.com.cn/speciality/detail.action?specId=tuqdmip7gpf5zcfc"
    }
  ],
  "requires_login_sections": [],
  "network_json_summaries": [
    {
      "index": 1,
      "url": "https://xz.chsi.com.cn/speciality/ksyx.action?specId=pisuaw667u74u5mo&ssdm=&schoolType=&_t=1776938947280",
      "status_code": 200,
      "resource_type": "xhr",
      "top_keys": [
        "data",
        "flag",
        "msg"
      ]
    },
    {
      "index": 2,
      "url": "https://xz.chsi.com.cn/ajax/getuserstatus.action?_t=1776938947295",
      "status_code": 200,
      "resource_type": "xhr",
      "top_keys": [
        "data",
        "flag",
        "msg"
      ]
    }
  ],
  "raw_files": {
    "html": "output/xz_detail/details/pisuaw667u74u5mo/page.html",
    "text": "output/xz_detail/details/pisuaw667u74u5mo/page.txt"
  }
}