{
  "index": 1,
  "url": "https://xz.chsi.com.cn/speciality/ksyx.action?specId=ic8byx5j0vhnzq9v&ssdm=&schoolType=&_t=1777019331578",
  "status_code": 200,
  "resource_type": "xhr",
  "json": {
    "data": [
      {
        "academeId": "315",
        "bxxz": "公办",
        "mydList": [
          {
            "count": 0,
            "rank": 0,
            "type": "3",
            "typeDesc": "综合满意度"
          },
          {
            "count": 2,
            "rank": 3,
            "type": "0",
            "typeDesc": "办学条件满意度"
          },
          {
            "count": 0,
            "rank": 0,
            "type": "1",
            "typeDesc": "教学质量满意度"
          },
          {
            "count": 0,
            "rank": 0,
            "type": "2",
            "typeDesc": "就业满意度"
          }
        ],
        "schId": "73395696",
        "yxdm": "10404",
        "yxmc": "华东交通大学",
        "yxmydList": [
          {
            "count": 5272,
            "rank": 4.2,
            "type": "2",
            "typeDesc": "综合满意度"
          },
          {
            "count": 6299,
            "rank": 4.4,
            "type": "0",
            "typeDesc": "院校环境满意度"
          },
          {
            "count": 5131,
            "rank": 3.7,
            "type": "1",
            "typeDesc": "生活满意度"
          }
        ],
        "zytjCount": 0,
        "zytjRank": 0
      },
      {
        "academeId": "629",
        "bxxz": "公办",
        "mydList": [
          {
            "count": 0,
            "rank": 0,
            "type": "3",
            "typeDesc": "综合满意度"
          },
          {
            "count": 6,
            "rank": 5,
            "type": "0",
            "typeDesc": "办学条件满意度"
          },
          {
            "count": 0,
            "rank": 0,
            "type": "1",
            "typeDesc": "教学质量满意度"
          },
          {
            "count": 0,
            "rank": 0,
            "type": "2",
            "typeDesc": "就业满意度"
          }
        ],
        "schId": "73394514",
        "yxdm": "10843",
        "yxmc": "郑州铁路职业技术学院",
        "yxmydList": [
          {
            "count": 3150,
            "rank": 4,
            "type": "2",
            "typeDesc": "综合满意度"
          },
          {
            "count": 4097,
            "rank": 3.9,
            "type": "0",
            "typeDesc": "院校环境满意度"
          },
          {
            "count": 2901,
            "rank": 3.7,
            "type": "1",
            "typeDesc": "生活满意度"
          }
        ],
        "zytjCount": 0,
        "zytjRank": 0
      },
      {
        "academeId": "1005",
        "bxxz": "公办",
        "mydList": [
          {
            "count": 1,
            "rank": 5,
            "type": "3",
            "typeDesc": "综合满意度"
          },
          {
            "count": 7,
            "rank": 4.9,
            "type": "0",
            "typeDesc": "办学条件满意度"
          },
          {
            "count": 1,
            "rank": 5,
            "type": "1",
            "typeDesc": "教学质量满意度"
          },
          {
            "count": 1,
            "rank": 5,
            "type": "2",
            "typeDesc": "就业满意度"
          }
        ],
        "schId": "73398186",
        "yxdm": "12302",
        "yxmc": "湖南铁道职业技术学院",
        "yxmydList": [
          {
            "count": 1897,
            "rank": 3.6,
            "type": "2",
            "typeDesc": "综合满意度"
          },
          {
            "count": 2494,
            "rank": 3.1,
            "type": "0",
            "typeDesc": "院校环境满意度"
          },
          {
            "count": 1794,
            "rank": 3,
            "type": "1",
            "typeDesc": "生活满意度"
          }
        ],
        "zytjCount": 0,
        "zytjRank": 0
      },
      {
        "academeId": "1019",
        "bxxz": "公办",
        "mydList": [
          {
            "count": 0,
            "rank": 0,
            "type": "3",
            "typeDesc": "综合满意度"
          },
          {
            "count": 3,
            "rank": 5,
            "type": "0",
            "typeDesc": "办学条件满意度"
          },
          {
            "count": 0,
            "rank": 0,
            "type": "1",
            "typeDesc": "教学质量满意度"
          },
          {
            "count": 0,
            "rank": 0,
            "type": "2",
            "typeDesc": "就业满意度"
          }
        ],
        "schId": "73398238",
        "yxdm": "12328",
        "yxmc": "山东职业学院",
        "yxmydList": [
          {
            "count": 2717,
            "rank": 4.4,
            "type": "2",
            "typeDesc": "综合满意度"
          },
          {
            "count": 3493,
            "rank": 4.4,
            "type": "0",
            "typeDesc": "院校环境满意度"
          },
          {
            "count": 2581,
            "rank": 4.2,
            "type": "1",
            "typeDesc": "生活满意度"
          }
        ],
        "zytjCount": 0,
        "zytjRank": 0
      },
      {
        "academeId": "1005905",
        "bxxz": "公办",
        "mydList": [
          {
            "count": 2,
            "rank": 4.5,
            "type": "3",
            "typeDesc": "综合满意度"
          },
          {
            "count": 5,
            "rank": 4.8,
            "type": "0",
            "typeDesc": "办学条件满意度"
          },
          {
            "count": 2,
            "rank": 5,
            "type": "1",
            "typeDesc": "教学质量满意度"
          },
          {
            "count": 2,
            "rank": 4.5,
            "type": "2",
            "typeDesc": "就业满意度"
          }
        ],
        "schId": "73398334",
        "yxdm": "12392",
        "yxmc": "柳州铁道职业技术学院",
        "yxmydList": [
          {
            "count": 1400,
            "rank": 3.8,
            "type": "2",
            "typeDesc": "综合满意度"
          },
          {
            "count": 1985,
            "rank": 3.8,
            "type": "0",
            "typeDesc": "院校环境满意度"
          },
          {
            "count": 1348,
            "rank": 3.5,
            "type": "1",
            "typeDesc": "生活满意度"
          }
        ],
        "zytjCount": 0,
        "zytjRank": 0
      },
      {
        "academeId": "1057",
        "bxxz": "公办",
        "mydList": [
          {
            "count": 4,
            "rank": 5,
            "type": "3",
            "typeDesc": "综合满意度"
          },
          {
            "count": 6,
            "rank": 4.3,
            "type": "0",
            "typeDesc": "办学条件满意度"
          },
          {
            "count": 3,
            "rank": 5,
            "type": "1",
            "typeDesc": "教学质量满意度"
          },
          {
            "count": 4,
            "rank": 4,
            "type": "2",
            "typeDesc": "就业满意度"
          }
        ],
        "schId": "73398374",
        "yxdm": "12424",
        "yxmc": "石家庄铁路职业技术学院",
        "yxmydList": [
          {
            "count": 2071,
            "rank": 4,
            "type": "2",
            "typeDesc": "综合满意度"
          },
          {
            "count": 2903,
            "rank": 3.6,
            "type": "0",
            "typeDesc": "院校环境满意度"
          },
          {
            "count": 1982,
            "rank": 3.6,
            "type": "1",
            "typeDesc": "生活满意度"
          }
        ],
        "zytjCount": 0,
        "zytjRank": 0
      },
      {
        "academeId": "1170",
        "bxxz": "公办",
        "mydList": [
          {
            "count": 0,
            "rank": 0,
            "type": "3",
            "typeDesc": "综合满意度"
          },
          {
            "count": 0,
            "rank": 0,
            "type": "0",
            "typeDesc": "办学条件满意度"
          },
          {
            "count": 0,
            "rank": 0,
            "type": "1",
            "typeDesc": "教学质量满意度"
          },
          {
            "count": 0,
            "rank": 0,
            "type": "2",
            "typeDesc": "就业满意度"
          }
        ],
        "schId": "73398818",
        "yxdm": "12670",
        "yxmc": "呼和浩特职业技术大学",
        "yxmydList": [
          {
            "count": 1726,
            "rank": 4,
            "type": "2",
            "typeDesc": "综合满意度"
          },
          {
            "count": 2135,
            "rank": 4.3,
            "type": "0",
            "typeDesc": "院校环境满意度"
          },
          {
            "count": 1607,
            "rank": 3.8,
            "type": "1",
            "typeDesc": "生活满意度"
          }
        ],
        "zytjCount": 0,
        "zytjRank": 0
      },
      {
        "academeId": "1323",
        "bxxz": "民办",
        "mydList": [
          {
            "count": 0,
            "rank": 0,
            "type": "3",
            "typeDesc": "综合满意度"
          },
          {
            "count": 3,
            "rank": 2.3,
            "type": "0",
            "typeDesc": "办学条件满意度"
          },
          {
            "count": 0,
            "rank": 0,
            "type": "1",
            "typeDesc": "教学质量满意度"
          },
          {
            "count": 0,
            "rank": 0,
            "type": "2",
            "typeDesc": "就业满意度"
          }
        ],
        "schId": "73389508",
        "yxdm": "12842",
        "yxmc": "德州科技职业学院",
        "yxmydList": [
          {
            "count": 0,
            "rank": 0,
            "type": "2",
            "typeDesc": "综合满意度"
          },
          {
            "count": 0,
            "rank": 0,
            "type": "0",
            "typeDesc": "院校环境满意度"
          },
          {
            "count": 0,
            "rank": 0,
            "type": "1",
            "typeDesc": "生活满意度"
          }
        ],
        "zytjCount": 0,
        "zytjRank": 0
      },
      {
        "academeId": "1369",
        "bxxz": "公办",
        "mydList": [
          {
            "count": 0,
            "rank": 0,
            "type": "3",
            "typeDesc": "综合满意度"
          },
          {
            "count": 4,
            "rank": 3.3,
            "type": "0",
            "typeDesc": "办学条件满意度"
          },
          {
            "count": 0,
            "rank": 0,
            "type": "1",
            "typeDesc": "教学质量满意度"
          },
          {
            "count": 0,
            "rank": 0,
            "type": "2",
            "typeDesc": "就业满意度"
          }
        ],
        "schId": "439532721",
        "yxdm": "12896",
        "yxmc": "辽宁轨道交通职业学院",
        "yxmydList": [
          {
            "count": 0,
            "rank": 0,
            "type": "2",
            "typeDesc": "综合满意度"
          },
          {
            "count": 0,
            "rank": 0,
            "type": "0",
            "typeDesc": "院校环境满意度"
          },
          {
            "count": 0,
            "rank": 0,
            "type": "1",
            "typeDesc": "生活满意度"
          }
        ],
        "zytjCount": 0,
        "zytjRank": 0
      },
      {
        "academeId": "1380",
        "bxxz": "公办",
        "mydList": [
          {
            "count": 0,
            "rank": 0,
            "type": "3",
            "typeDesc": "综合满意度"
          },
          {
            "count": 0,
            "rank": 0,
            "type": "0",
            "typeDesc": "办学条件满意度"
          },
          {
            "count": 0,
            "rank": 0,
            "type": "1",
            "typeDesc": "教学质量满意度"
          },
          {
            "count": 0,
            "rank": 0,
            "type": "2",
            "typeDesc": "就业满意度"
          }
        ],
        "schId": "73389708",
        "yxdm": "12907",
        "yxmc": "哈尔滨铁道职业技术学院",
        "yxmydList": [
          {
            "count": 2466,
            "rank": 3.8,
            "type": "2",
            "typeDesc": "综合满意度"
          },
          {
            "count": 2955,
            "rank": 3.5,
            "type": "0",
            "typeDesc": "院校环境满意度"
          },
          {
            "count": 2274,
            "rank": 3.4,
            "type": "1",
            "typeDesc": "生活满意度"
          }
        ],
        "zytjCount": 0,
        "zytjRank": 0
      },
      {
        "academeId": "1449",
        "bxxz": "公办",
        "mydList": [
          {
            "count": 3,
            "rank": 5,
            "type": "3",
            "typeDesc": "综合满意度"
          },
          {
            "count": 9,
            "rank": 5,
            "type": "0",
            "typeDesc": "办学条件满意度"
          },
          {
            "count": 3,
            "rank": 5,
            "type": "1",
            "typeDesc": "教学质量满意度"
          },
          {
            "count": 3,
            "rank": 5,
            "type": "2",
            "typeDesc": "就业满意度"
          }
        ],
        "schId": "73389948",
        "yxdm": "12977",
        "yxmc": "武汉铁路职业技术学院",
        "yxmydList": [
          {
            "count": 1613,
            "rank": 4,
            "type": "2",
            "typeDesc": "综合满意度"
          },
          {
            "count": 2385,
            "rank": 3.9,
            "type": "0",
            "typeDesc": "院校环境满意度"
          },
          {
            "count": 1519,
            "rank": 3.7,
            "type": "1",
            "typeDesc": "生活满意度"
          }
        ],
        "zytjCount": 0,
        "zytjRank": 0
      },
      {
        "academeId": "1537",
        "bxxz": "公办",
        "mydList": [
          {
            "count": 0,
            "rank": 0,
            "type": "3",
            "typeDesc": "综合满意度"
          },
          {
            "count": 6,
            "rank": 4.2,
            "type": "0",
            "typeDesc": "办学条件满意度"
          },
          {
            "count": 0,
            "rank": 0,
            "type": "1",
            "typeDesc": "教学质量满意度"
          },
          {
            "count": 0,
            "rank": 0,
            "type": "2",
            "typeDesc": "就业满意度"
          }
        ],
        "schId": "73390280",
        "yxdm": "13106",
        "yxmc": "南京铁道职业技术学院",
        "yxmydList": [
          {
            "count": 937,
            "rank": 4.2,
            "type": "2",
            "typeDesc": "综合满意度"
          },
          {
            "count": 1472,
            "rank": 4.2,
            "type": "0",
            "typeDesc": "院校环境满意度"
          },
          {
            "count": 894,
            "rank": 4,
            "type": "1",
            "typeDesc": "生活满意度"
          }
        ],
        "zytjCount": 0,
        "zytjRank": 0
      },
      {
        "academeId": "1718",
        "bxxz": "民办",
        "mydList": [
          {
            "count": 3,
            "rank": 5,
            "type": "3",
            "typeDesc": "综合满意度"
          },
          {
            "count": 7,
            "rank": 4.4,
            "type": "0",
            "typeDesc": "办学条件满意度"
          },
          {
            "count": 3,
            "rank": 5,
            "type": "1",
            "typeDesc": "教学质量满意度"
          },
          {
            "count": 3,
            "rank": 5,
            "type": "2",
            "typeDesc": "就业满意度"
          }
        ],
        "schId": "73390808",
        "yxdm": "13399",
        "yxmc": "石家庄工商职业学院",
        "yxmydList": [
          {
            "count": 1035,
            "rank": 4,
            "type": "2",
            "typeDesc": "综合满意度"
          },
          {
            "count": 1606,
            "rank": 4,
            "type": "0",
            "typeDesc": "院校环境满意度"
          },
          {
            "count": 994,
            "rank": 3.8,
            "type": "1",
            "typeDesc": "生活满意度"
          }
        ],
        "zytjCount": 0,
        "zytjRank": 0
      },
      {
        "academeId": "1816",
        "bxxz": "公办",
        "mydList": [
          {
            "count": 0,
            "rank": 0,
            "type": "3",
            "typeDesc": "综合满意度"
          },
          {
            "count": 4,
            "rank": 4,
            "type": "0",
            "typeDesc": "办学条件满意度"
          },
          {
            "count": 1,
            "rank": 5,
            "type": "1",
            "typeDesc": "教学质量满意度"
          },
          {
            "count": 0,
            "rank": 0,
            "type": "2",
            "typeDesc": "就业满意度"
          }
        ],
        "schId": "73391156",
        "yxdm": "13566",
        "yxmc": "陕西铁路工程职业技术学院",
        "yxmydList": [
          {
            "count": 3293,
            "rank": 4.2,
            "type": "2",
            "typeDesc": "综合满意度"
          },
          {
            "count": 4445,
            "rank": 4.1,
            "type": "0",
            "typeDesc": "院校环境满意度"
          },
          {
            "count": 3104,
            "rank": 4,
            "type": "1",
            "typeDesc": "生活满意度"
          }
        ],
        "zytjCount": 0,
        "zytjRank": 0
      },
      {
        "academeId": "2091",
        "bxxz": "民办",
        "mydList": [
          {
            "count": 0,
            "rank": 0,
            "type": "3",
            "typeDesc": "综合满意度"
          },
          {
            "count": 1,
            "rank": 5,
            "type": "0",
            "typeDesc": "办学条件满意度"
          },
          {
            "count": 0,
            "rank": 0,
            "type": "1",
            "typeDesc": "教学质量满意度"
          },
          {
            "count": 0,
            "rank": 0,
            "type": "2",
            "typeDesc": "就业满意度"
          }
        ],
        "schId": "73392204",
        "yxdm": "13862",
        "yxmc": "山西同文职业技术学院",
        "yxmydList": [
          {
            "count": 585,
            "rank": 3.6,
            "type": "2",
            "typeDesc": "综合满意度"
          },
          {
            "count": 1003,
            "rank": 3.6,
            "type": "0",
            "typeDesc": "院校环境满意度"
          },
          {
            "count": 544,
            "rank": 3.5,
            "type": "1",
            "typeDesc": "生活满意度"
          }
        ],
        "zytjCount": 0,
        "zytjRank": 0
      },
      {
        "academeId": "403132",
        "bxxz": "公办",
        "mydList": [
          {
            "count": 0,
            "rank": 0,
            "type": "3",
            "typeDesc": "综合满意度"
          },
          {
            "count": 0,
            "rank": 0,
            "type": "0",
            "typeDesc": "办学条件满意度"
          },
          {
            "count": 0,
            "rank": 0,
            "type": "1",
            "typeDesc": "教学质量满意度"
          },
          {
            "count": 0,
            "rank": 0,
            "type": "2",
            "typeDesc": "就业满意度"
          }
        ],
        "schId": "73392208",
        "yxdm": "13863",
        "yxmc": "天津铁道职业技术学院",
        "yxmydList": [
          {
            "count": 1472,
            "rank": 3.7,
            "type": "2",
            "typeDesc": "综合满意度"
          },
          {
            "count": 1947,
            "rank": 3.7,
            "type": "0",
            "typeDesc": "院校环境满意度"
          },
          {
            "count": 1399,
            "rank": 3.1,
            "type": "1",
            "typeDesc": "生活满意度"
          }
        ],
        "zytjCount": 0,
        "zytjRank": 0
      },
      {
        "academeId": "398547",
        "bxxz": "公办",
        "mydList": [
          {
            "count": 2,
            "rank": 1.5,
            "type": "3",
            "typeDesc": "综合满意度"
          },
          {
            "count": 6,
            "rank": 2.7,
            "type": "0",
            "typeDesc": "办学条件满意度"
          },
          {
            "count": 2,
            "rank": 2,
            "type": "1",
            "typeDesc": "教学质量满意度"
          },
          {
            "count": 2,
            "rank": 1,
            "type": "2",
            "typeDesc": "就业满意度"
          }
        ],
        "schId": "73392452",
        "yxdm": "13941",
        "yxmc": "湖南高速铁路职业技术学院",
        "yxmydList": [
          {
            "count": 1319,
            "rank": 3.9,
            "type": "2",
            "typeDesc": "综合满意度"
          },
          {
            "count": 2012,
            "rank": 3.7,
            "type": "0",
            "typeDesc": "院校环境满意度"
          },
          {
            "count": 1237,
            "rank": 3.6,
            "type": "1",
            "typeDesc": "生活满意度"
          }
        ],
        "zytjCount": 0,
        "zytjRank": 0
      },
      {
        "academeId": "405289",
        "bxxz": "公办",
        "mydList": [
          {
            "count": 0,
            "rank": 0,
            "type": "3",
            "typeDesc": "综合满意度"
          },
          {
            "count": 0,
            "rank": 0,
            "type": "0",
            "typeDesc": "办学条件满意度"
          },
          {
            "count": 0,
            "rank": 0,
            "type": "1",
            "typeDesc": "教学质量满意度"
          },
          {
            "count": 0,
            "rank": 0,
            "type": "2",
            "typeDesc": "就业满意度"
          }
        ],
        "schId": "73392456",
        "yxdm": "13942",
        "yxmc": "湖南铁路科技职业技术学院",
        "yxmydList": [
          {
            "count": 1472,
            "rank": 3.8,
            "type": "2",
            "typeDesc": "综合满意度"
          },
          {
            "count": 1913,
            "rank": 3.8,
            "type": "0",
            "typeDesc": "院校环境满意度"
          },
          {
            "count": 1375,
            "rank": 3.4,
            "type": "1",
            "typeDesc": "生活满意度"
          }
        ],
        "zytjCount": 0,
        "zytjRank": 0
      },
      {
        "academeId": "6196002",
        "bxxz": "公办",
        "mydList": [
          {
            "count": 0,
            "rank": 0,
            "type": "3",
            "typeDesc": "综合满意度"
          },
          {
            "count": 2,
            "rank": 4,
            "type": "0",
            "typeDesc": "办学条件满意度"
          },
          {
            "count": 0,
            "rank": 0,
            "type": "1",
            "typeDesc": "教学质量满意度"
          },
          {
            "count": 0,
            "rank": 0,
            "type": "2",
            "typeDesc": "就业满意度"
          }
        ],
        "schId": "73392460",
        "yxdm": "13943",
        "yxmc": "广州铁路职业技术学院",
        "yxmydList": [
          {
            "count": 1259,
            "rank": 3.4,
            "type": "2",
            "typeDesc": "综合满意度"
          },
          {
            "count": 1627,
            "rank": 2.9,
            "type": "0",
            "typeDesc": "院校环境满意度"
          },
          {
            "count": 1198,
            "rank": 2.9,
            "type": "1",
            "typeDesc": "生活满意度"
          }
        ],
        "zytjCount": 0,
        "zytjRank": 0
      },
      {
        "academeId": "4995422",
        "bxxz": "公办",
        "mydList": [
          {
            "count": 86,
            "rank": 5,
            "type": "3",
            "typeDesc": "综合满意度"
          },
          {
            "count": 144,
            "rank": 4.8,
            "type": "0",
            "typeDesc": "办学条件满意度"
          },
          {
            "count": 88,
            "rank": 5,
            "type": "1",
            "typeDesc": "教学质量满意度"
          },
          {
            "count": 87,
            "rank": 5,
            "type": "2",
            "typeDesc": "就业满意度"
          }
        ],
        "schId": "73392464",
        "yxdm": "13945",
        "yxmc": "西安铁路职业技术学院",
        "yxmydList": [
          {
            "count": 2878,
            "rank": 3.9,
            "type": "2",
            "typeDesc": "综合满意度"
          },
          {
            "count": 4230,
            "rank": 3.6,
            "type": "0",
            "typeDesc": "院校环境满意度"
          },
          {
            "count": 2862,
            "rank": 3.5,
            "type": "1",
            "typeDesc": "生活满意度"
          }
        ],
        "zytjCount": 0,
        "zytjRank": 0
      },
      {
        "academeId": "5451024",
        "bxxz": "公办",
        "mydList": [
          {
            "count": 1,
            "rank": 5,
            "type": "3",
            "typeDesc": "综合满意度"
          },
          {
            "count": 3,
            "rank": 5,
            "type": "0",
            "typeDesc": "办学条件满意度"
          },
          {
            "count": 1,
            "rank": 5,
            "type": "1",
            "typeDesc": "教学质量满意度"
          },
          {
            "count": 1,
            "rank": 5,
            "type": "2",
            "typeDesc": "就业满意度"
          }
        ],
        "schId": "73392684",
        "yxdm": "14006",
        "yxmc": "四川铁道职业学院",
        "yxmydList": [
          {
            "count": 688,
            "rank": 3.6,
            "type": "2",
            "typeDesc": "综合满意度"
          },
          {
            "count": 999,
            "rank": 3.6,
            "type": "0",
            "typeDesc": "院校环境满意度"
          },
          {
            "count": 641,
            "rank": 3.4,
            "type": "1",
            "typeDesc": "生活满意度"
          }
        ],
        "zytjCount": 0,
        "zytjRank": 0
      },
      {
        "academeId": "6241953",
        "bxxz": "公办",
        "mydList": [
          {
            "count": 0,
            "rank": 0,
            "type": "3",
            "typeDesc": "综合满意度"
          },
          {
            "count": 0,
            "rank": 0,
            "type": "0",
            "typeDesc": "办学条件满意度"
          },
          {
            "count": 0,
            "rank": 0,
            "type": "1",
            "typeDesc": "教学质量满意度"
          },
          {
            "count": 0,
            "rank": 0,
            "type": "2",
            "typeDesc": "就业满意度"
          }
        ],
        "schId": "73392832",
        "yxdm": "14052",
        "yxmc": "吉林铁道职业技术大学",
        "yxmydList": [
          {
            "count": 1050,
            "rank": 3.9,
            "type": "2",
            "typeDesc": "综合满意度"
          },
          {
            "count": 1665,
            "rank": 4.1,
            "type": "0",
            "typeDesc": "院校环境满意度"
          },
          {
            "count": 968,
            "rank": 3.6,
            "type": "1",
            "typeDesc": "生活满意度"
          }
        ],
        "zytjCount": 0,
        "zytjRank": 0
      },
      {
        "academeId": "5571032",
        "bxxz": "公办",
        "mydList": [
          {
            "count": 1,
            "rank": 1,
            "type": "3",
            "typeDesc": "综合满意度"
          },
          {
            "count": 9,
            "rank": 3.2,
            "type": "0",
            "typeDesc": "办学条件满意度"
          },
          {
            "count": 2,
            "rank": 5,
            "type": "1",
            "typeDesc": "教学质量满意度"
          },
          {
            "count": 1,
            "rank": 1,
            "type": "2",
            "typeDesc": "就业满意度"
          }
        ],
        "schId": "73392836",
        "yxdm": "14053",
        "yxmc": "黑龙江交通职业技术学院",
        "yxmydList": [
          {
            "count": 1315,
            "rank": 3.6,
            "type": "2",
            "typeDesc": "综合满意度"
          },
          {
            "count": 2095,
            "rank": 3.2,
            "type": "0",
            "typeDesc": "院校环境满意度"
          },
          {
            "count": 1254,
            "rank": 3.3,
            "type": "1",
            "typeDesc": "生活满意度"
          }
        ],
        "zytjCount": 0,
        "zytjRank": 0
      },
      {
        "academeId": "5542448",
        "bxxz": "公办",
        "mydList": [
          {
            "count": 4,
            "rank": 3.8,
            "type": "3",
            "typeDesc": "综合满意度"
          },
          {
            "count": 21,
            "rank": 4.3,
            "type": "0",
            "typeDesc": "办学条件满意度"
          },
          {
            "count": 5,
            "rank": 4.2,
            "type": "1",
            "typeDesc": "教学质量满意度"
          },
          {
            "count": 4,
            "rank": 3.8,
            "type": "2",
            "typeDesc": "就业满意度"
          }
        ],
        "schId": "73393109",
        "yxdm": "14129",
        "yxmc": "贵阳职业技术学院",
        "yxmydList": [
          {
            "count": 1389,
            "rank": 3.5,
            "type": "2",
            "typeDesc": "综合满意度"
          },
          {
            "count": 1977,
            "rank": 3.8,
            "type": "0",
            "typeDesc": "院校环境满意度"
          },
          {
            "count": 1362,
            "rank": 2.8,
            "type": "1",
            "typeDesc": "生活满意度"
          }
        ],
        "zytjCount": 0,
        "zytjRank": 0
      },
      {
        "academeId": "6238908",
        "bxxz": "公办",
        "mydList": [
          {
            "count": 3,
            "rank": 4,
            "type": "3",
            "typeDesc": "综合满意度"
          },
          {
            "count": 6,
            "rank": 3,
            "type": "0",
            "typeDesc": "办学条件满意度"
          },
          {
            "count": 3,
            "rank": 3.7,
            "type": "1",
            "typeDesc": "教学质量满意度"
          },
          {
            "count": 3,
            "rank": 4.7,
            "type": "2",
            "typeDesc": "就业满意度"
          }
        ],
        "schId": "73393241",
        "yxdm": "14187",
        "yxmc": "包头铁道职业技术学院",
        "yxmydList": [
          {
            "count": 615,
            "rank": 3.6,
            "type": "2",
            "typeDesc": "综合满意度"
          },
          {
            "count": 992,
            "rank": 3.6,
            "type": "0",
            "typeDesc": "院校环境满意度"
          },
          {
            "count": 580,
            "rank": 3.3,
            "type": "1",
            "typeDesc": "生活满意度"
          }
        ],
        "zytjCount": 0,
        "zytjRank": 0
      },
      {
        "academeId": "18914485",
        "bxxz": "公办",
        "mydList": [
          {
            "count": 1,
            "rank": 5,
            "type": "3",
            "typeDesc": "综合满意度"
          },
          {
            "count": 10,
            "rank": 3.8,
            "type": "0",
            "typeDesc": "办学条件满意度"
          },
          {
            "count": 1,
            "rank": 5,
            "type": "1",
            "typeDesc": "教学质量满意度"
          },
          {
            "count": 2,
            "rank": 4.5,
            "type": "2",
            "typeDesc": "就业满意度"
          }
        ],
        "schId": "73393245",
        "yxdm": "14188",
        "yxmc": "辽宁铁道职业技术学院",
        "yxmydList": [
          {
            "count": 774,
            "rank": 4.1,
            "type": "2",
            "typeDesc": "综合满意度"
          },
          {
            "count": 1199,
            "rank": 4.1,
            "type": "0",
            "typeDesc": "院校环境满意度"
          },
          {
            "count": 723,
            "rank": 3.9,
            "type": "1",
            "typeDesc": "生活满意度"
          }
        ],
        "zytjCount": 0,
        "zytjRank": 0
      },
      {
        "academeId": "48744058",
        "bxxz": "民办",
        "mydList": [
          {
            "count": 4,
            "rank": 3.8,
            "type": "3",
            "typeDesc": "综合满意度"
          },
          {
            "count": 11,
            "rank": 3.8,
            "type": "0",
            "typeDesc": "办学条件满意度"
          },
          {
            "count": 4,
            "rank": 3.8,
            "type": "1",
            "typeDesc": "教学质量满意度"
          },
          {
            "count": 4,
            "rank": 3.8,
            "type": "2",
            "typeDesc": "就业满意度"
          }
        ],
        "schId": "73394090",
        "yxdm": "14265",
        "yxmc": "广东南方职业学院",
        "yxmydList": [
          {
            "count": 1707,
            "rank": 3.4,
            "type": "2",
            "typeDesc": "综合满意度"
          },
          {
            "count": 2761,
            "rank": 3.5,
            "type": "0",
            "typeDesc": "院校环境满意度"
          },
          {
            "count": 1649,
            "rank": 3.3,
            "type": "1",
            "typeDesc": "生活满意度"
          }
        ],
        "zytjCount": 0,
        "zytjRank": 0
      },
      {
        "academeId": "174278201",
        "bxxz": "民办",
        "mydList": [
          {
            "count": 0,
            "rank": 0,
            "type": "3",
            "typeDesc": "综合满意度"
          },
          {
            "count": 0,
            "rank": 0,
            "type": "0",
            "typeDesc": "办学条件满意度"
          },
          {
            "count": 0,
            "rank": 0,
            "type": "1",
            "typeDesc": "教学质量满意度"
          },
          {
            "count": 0,
            "rank": 0,
            "type": "2",
            "typeDesc": "就业满意度"
          }
        ],
        "schId": "203682090",
        "yxdm": "14337",
        "yxmc": "内蒙古能源职业学院",
        "yxmydList": [
          {
            "count": 0,
            "rank": 0,
            "type": "2",
            "typeDesc": "综合满意度"
          },
          {
            "count": 0,
            "rank": 0,
            "type": "0",
            "typeDesc": "院校环境满意度"
          },
          {
            "count": 0,
            "rank": 0,
            "type": "1",
            "typeDesc": "生活满意度"
          }
        ],
        "zytjCount": 0,
        "zytjRank": 0
      },
      {
        "academeId": "174264277",
        "bxxz": "民办",
        "mydList": [
          {
            "count": 34,
            "rank": 5,
            "type": "3",
            "typeDesc": "综合满意度"
          },
          {
            "count": 52,
            "rank": 4.9,
            "type": "0",
            "typeDesc": "办学条件满意度"
          },
          {
            "count": 33,
            "rank": 5,
            "type": "1",
            "typeDesc": "教学质量满意度"
          },
          {
            "count": 33,
            "rank": 4.8,
            "type": "2",
            "typeDesc": "就业满意度"
          }
        ],
        "schId": "203682078",
        "yxdm": "14366",
        "yxmc": "重庆公共运输职业学院",
        "yxmydList": [
          {
            "count": 4252,
            "rank": 4.3,
            "type": "2",
            "typeDesc": "综合满意度"
          },
          {
            "count": 5652,
            "rank": 4.3,
            "type": "0",
            "typeDesc": "院校环境满意度"
          },
          {
            "count": 4070,
            "rank": 4.2,
            "type": "1",
            "typeDesc": "生活满意度"
          }
        ],
        "zytjCount": 0,
        "zytjRank": 0
      },
      {
        "academeId": "349045811",
        "bxxz": "公办",
        "mydList": [
          {
            "count": 2,
            "rank": 5,
            "type": "3",
            "typeDesc": "综合满意度"
          },
          {
            "count": 6,
            "rank": 3.7,
            "type": "0",
            "typeDesc": "办学条件满意度"
          },
          {
            "count": 2,
            "rank": 5,
            "type": "1",
            "typeDesc": "教学质量满意度"
          },
          {
            "count": 2,
            "rank": 5,
            "type": "2",
            "typeDesc": "就业满意度"
          }
        ],
        "schId": "306571973",
        "yxdm": "14396",
        "yxmc": "河北轨道运输职业技术学院",
        "yxmydList": [
          {
            "count": 579,
            "rank": 3.6,
            "type": "2",
            "typeDesc": "综合满意度"
          },
          {
            "count": 1155,
            "rank": 3.6,
            "type": "0",
            "typeDesc": "院校环境满意度"
          },
          {
            "count": 553,
            "rank": 3.3,
            "type": "1",
            "typeDesc": "生活满意度"
          }
        ],
        "zytjCount": 0,
        "zytjRank": 0
      },
      {
        "academeId": "609659719",
        "bxxz": "公办",
        "mydList": [
          {
            "count": 1,
            "rank": 1,
            "type": "3",
            "typeDesc": "综合满意度"
          },
          {
            "count": 2,
            "rank": 3,
            "type": "0",
            "typeDesc": "办学条件满意度"
          },
          {
            "count": 1,
            "rank": 1,
            "type": "1",
            "typeDesc": "教学质量满意度"
          },
          {
            "count": 1,
            "rank": 1,
            "type": "2",
            "typeDesc": "就业满意度"
          }
        ],
        "schId": "427459136",
        "yxdm": "14489",
        "yxmc": "新疆铁道职业技术学院",
        "yxmydList": [
          {
            "count": 344,
            "rank": 3,
            "type": "2",
            "typeDesc": "综合满意度"
          },
          {
            "count": 725,
            "rank": 3.2,
            "type": "0",
            "typeDesc": "院校环境满意度"
          },
          {
            "count": 333,
            "rank": 2.7,
            "type": "1",
            "typeDesc": "生活满意度"
          }
        ],
        "zytjCount": 0,
        "zytjRank": 0
      },
      {
        "academeId": "969065309",
        "bxxz": "公办",
        "mydList": [
          {
            "count": 0,
            "rank": 0,
            "type": "3",
            "typeDesc": "综合满意度"
          },
          {
            "count": 2,
            "rank": 5,
            "type": "0",
            "typeDesc": "办学条件满意度"
          },
          {
            "count": 0,
            "rank": 0,
            "type": "1",
            "typeDesc": "教学质量满意度"
          },
          {
            "count": 1,
            "rank": 5,
            "type": "2",
            "typeDesc": "就业满意度"
          }
        ],
        "schId": "951413073",
        "yxdm": "14514",
        "yxmc": "成都工业职业技术学院",
        "yxmydList": [
          {
            "count": 176,
            "rank": 3,
            "type": "2",
            "typeDesc": "综合满意度"
          },
          {
            "count": 152,
            "rank": 3.3,
            "type": "0",
            "typeDesc": "院校环境满意度"
          },
          {
            "count": 151,
            "rank": 2.6,
            "type": "1",
            "typeDesc": "生活满意度"
          }
        ],
        "zytjCount": 0,
        "zytjRank": 0
      },
      {
        "academeId": "1447964274",
        "bxxz": "公办",
        "mydList": [
          {
            "count": 1,
            "rank": 5,
            "type": "3",
            "typeDesc": "综合满意度"
          },
          {
            "count": 9,
            "rank": 3.2,
            "type": "0",
            "typeDesc": "办学条件满意度"
          },
          {
            "count": 1,
            "rank": 5,
            "type": "1",
            "typeDesc": "教学质量满意度"
          },
          {
            "count": 1,
            "rank": 5,
            "type": "2",
            "typeDesc": "就业满意度"
          }
        ],
        "schId": "blbx7gq6egr1gzhf",
        "yxdm": "14547",
        "yxmc": "成都工贸职业技术学院",
        "yxmydList": [
          {
            "count": 0,
            "rank": 0,
            "type": "2",
            "typeDesc": "综合满意度"
          },
          {
            "count": 0,
            "rank": 0,
            "type": "0",
            "typeDesc": "院校环境满意度"
          },
          {
            "count": 0,
            "rank": 0,
            "type": "1",
            "typeDesc": "生活满意度"
          }
        ],
        "zytjCount": 0,
        "zytjRank": 0
      },
      {
        "academeId": "2024107115",
        "bxxz": "民办",
        "mydList": [
          {
            "count": 4,
            "rank": 4,
            "type": "3",
            "typeDesc": "综合满意度"
          },
          {
            "count": 7,
            "rank": 3.9,
            "type": "0",
            "typeDesc": "办学条件满意度"
          },
          {
            "count": 4,
            "rank": 3.8,
            "type": "1",
            "typeDesc": "教学质量满意度"
          },
          {
            "count": 4,
            "rank": 3.5,
            "type": "2",
            "typeDesc": "就业满意度"
          }
        ],
        "schId": "1blai386sdrsdnpy",
        "yxdm": "14642",
        "yxmc": "德阳城市轨道交通职业学院",
        "yxmydList": [
          {
            "count": 136,
            "rank": 3.6,
            "type": "2",
            "typeDesc": "综合满意度"
          },
          {
            "count": 335,
            "rank": 3.6,
            "type": "0",
            "typeDesc": "院校环境满意度"
          },
          {
            "count": 139,
            "rank": 3.4,
            "type": "1",
            "typeDesc": "生活满意度"
          }
        ],
        "zytjCount": 0,
        "zytjRank": 0
      },
      {
        "academeId": "3156266380",
        "bxxz": "公办",
        "mydList": [
          {
            "count": 1,
            "rank": 5,
            "type": "3",
            "typeDesc": "综合满意度"
          },
          {
            "count": 3,
            "rank": 5,
            "type": "0",
            "typeDesc": "办学条件满意度"
          },
          {
            "count": 1,
            "rank": 5,
            "type": "1",
            "typeDesc": "教学质量满意度"
          },
          {
            "count": 1,
            "rank": 5,
            "type": "2",
            "typeDesc": "就业满意度"
          }
        ],
        "schId": "m69sajpkjb1yokw6",
        "yxdm": "51759",
        "yxmc": "重庆工信职业学院",
        "yxmydList": [
          {
            "count": 0,
            "rank": 0,
            "type": "2",
            "typeDesc": "综合满意度"
          },
          {
            "count": 0,
            "rank": 0,
            "type": "0",
            "typeDesc": "院校环境满意度"
          },
          {
            "count": 0,
            "rank": 0,
            "type": "1",
            "typeDesc": "生活满意度"
          }
        ],
        "zytjCount": 7,
        "zytjRank": 4.4
      }
    ],
    "flag": true,
    "msg": ""
  }
}